{
  "account_info": {
    "totalWalletBalance": "10188.053519970596",
    "availableBalance": "5717.483519970596",
    "totalUnrealizedProfit": "-76.17879970652211",
    "totalMarginBalance": "10111.874720264073",
    "assets": [
      {
        "asset": "USDT",
        "walletBalance": "10188.053519970596",
        "availableBalance": "5717.483519970596",
        "unrealizedProfit": "-76.17879970652211",
        "marginBalance": "10111.874720264073"
      }
    ],
    "positions": [
      {
        "symbol": "BTCUSDT",
        "positionSide": "SHORT",
        "positionAmt": "-0.05",
        "entryPrice": "87887.82400586955",
        "markPrice": "89411.4",
        "unRealizedProfit": "-76.17879970652211",
        "leverage": "1",
        "isolatedMargin": "4394.391200293478",
        "liquidationPrice": "0.0"
      }
    ]
  },
  "account_snapshot": {
    "balance": 10188.053519970596,
    "available_balance": 5717.483519970596,
    "total_equity": 10111.874720264073,
    "unrealized_pnl": -76.17879970652211,
    "used_margin": 4394.391200293478,
    "open_orders_count": 0,
    "positions_count": 1
  },
  "stats": {
    "initial_balance": 10000.0,
    "current_balance": 10188.053519970596,
    "total_equity": 10111.874720264073,
    "total_return": 1.1187472026407341,
    "total_trades": 109,
    "winning_trades": 34,
    "losing_trades": 20,
    "win_rate": 31.19266055045872,
    "total_commission": 197.7725834003497,
    "total_realized_pnl": 385.826103370946,
    "max_drawdown": 3.8202303042599075,
    "peak_balance": 10203.248517694481
  },
  "trades": [
    {
      "tradeId": "713AD42C",
      "orderId": "FBA24F76",
      "symbol": "BTCUSDT",
      "side": "SELL",
      "price": "87593.95597484353",
      "qty": "0.05",
      "commission": "1.7518791194968708",
      "realizedPnl": "0.0",
      "time": 1776775369236
    },
    {
      "tradeId": "8C1AEF51",
      "orderId": "614E6F5F",
      "symbol": "BTCUSDT",
      "side": "BUY",
      "price": "87530.53513977288",
      "qty": "0.05",
      "commission": "1.7506107027954578",
      "realizedPnl": "3.171041753532336",
      "time": 1776775369351
    },
    {
      "tradeId": "30479BA8",
      "orderId": "36FB3347",
      "symbol": "BTCUSDT",
      "side": "BUY",
      "price": "87530.53513977288",
      "qty": "0.05",
      "commission": "1.7506107027954578",
      "realizedPnl": "0.0",
      "time": 1776775369352
    },
    {
      "tradeId": "A1E6205D",
      "orderId": "A652EF31",
      "symbol": "BTCUSDT",
      "side": "SELL",
      "price": "87952.8169343278",
      "qty": "0.05",
      "commission": "1.759056338686556",
      "realizedPnl": "21.11408972774589",
      "time": 1776775369376
    },
    {
      "tradeId": "165FF9AB",
      "orderId": "4AB78861",
      "symbol": "BTCUSDT",
      "side": "SELL",
      "price": "87952.8169343278",
      "qty": "0.05",
      "commission": "1.759056338686556",
      "realizedPnl": "0.0",
      "time": 1776775369377
    },
    {
      "tradeId": "3C669619",
      "orderId": "E677D22D",
      "symbol": "BTCUSDT",
      "side": "BUY",
      "price": "87539.03606416969",
      "qty": "0.05",
      "commission": "1.750780721283394",
      "realizedPnl": "20.689043507905446",
      "time": 1776775369393
    },
    {
      "tradeId": "C3621D17",
      "orderId": "B97931DC",
      "symbol": "BTCUSDT",
      "side": "BUY",
      "price": "87539.03606416969",
      "qty": "0.05",
      "commission": "1.750780721283394",
      "realizedPnl": "0.0",
      "time": 1776775369394
    },
    {
      "tradeId": "95DA2799",
      "orderId": "3EB0A572",
      "symbol": "BTCUSDT",
      "side": "SELL",
      "price": "89142.48741782784",
      "qty": "0.05",
      "commission": "1.782849748356557",
      "realizedPnl": "80.17256768290754",
      "time": 1776775369652
    },
    {
      "tradeId": "B8510916",
      "orderId": "3BD2D70F",
      "symbol": "BTCUSDT",
      "side": "SELL",
      "price": "89142.48741782784",
      "qty": "0.05",
      "commission": "1.782849748356557",
      "realizedPnl": "0.0",
      "time": 1776775369653
    },
    {
      "tradeId": "38E79506",
      "orderId": "703D8317",
      "symbol": "BTCUSDT",
      "side": "BUY",
      "price": "87556.83799998877",
      "qty": "0.05",
      "commission": "1.7511367599997754",
      "realizedPnl": "79.28247089195357",
      "time": 1776775369858
    },
    {
      "tradeId": "9661F492",
      "orderId": "DD76816F",
      "symbol": "BTCUSDT",
      "side": "BUY",
      "price": "87556.83799998877",
      "qty": "0.05",
      "commission": "1.7511367599997754",
      "realizedPnl": "0.0",
      "time": 1776775369858
    },
    {
      "tradeId": "3515E3C7",
      "orderId": "EBE2F48E",
      "symbol": "BTCUSDT",
      "side": "SELL",
      "price": "87614.35375611238",
      "qty": "0.05",
      "commission": "1.7522870751222477",
      "realizedPnl": "2.875787806180597",
      "time": 1776775370138
    },
    {
      "tradeId": "77F7025D",
      "orderId": "76071D6A",
      "symbol": "BTCUSDT",
      "side": "SELL",
      "price": "87614.35375611238",
      "qty": "0.05",
      "commission": "1.7522870751222477",
      "realizedPnl": "0.0",
      "time": 1776775370139
    },
    {
      "tradeId": "B76DE4A6",
      "orderId": "DDD401D9",
      "symbol": "BTCUSDT",
      "side": "BUY",
      "price": "87693.05281331595",
      "qty": "0.05",
      "commission": "1.753861056266319",
      "realizedPnl": "-3.934952860178601",
      "time": 1776775370222
    },
    {
      "tradeId": "6E646FA4",
      "orderId": "4D29A0A8",
      "symbol": "BTCUSDT",
      "side": "BUY",
      "price": "87693.05281331595",
      "qty": "0.05",
      "commission": "1.753861056266319",
      "realizedPnl": "0.0",
      "time": 1776775370223
    },
    {
      "tradeId": "2FAB9F9C",
      "orderId": "913AE5C6",
      "symbol": "BTCUSDT",
      "side": "SELL",
      "price": "88252.98426920256",
      "qty": "0.05",
      "commission": "1.7650596853840512",
      "realizedPnl": "27.996572794330135",
      "time": 1776775370445
    },
    {
      "tradeId": "7E336BC4",
      "orderId": "6B766CE3",
      "symbol": "BTCUSDT",
      "side": "SELL",
      "price": "88252.98426920256",
      "qty": "0.05",
      "commission": "1.7650596853840512",
      "realizedPnl": "0.0",
      "time": 1776775370446
    },
    {
      "tradeId": "D6A64660",
      "orderId": "931889C0",
      "symbol": "BTCUSDT",
      "side": "BUY",
      "price": "89750.07673966182",
      "qty": "0.05",
      "commission": "1.7950015347932364",
      "realizedPnl": "-74.85462352296308",
      "time": 1776775370506
    },
    {
      "tradeId": "BC18F46E",
      "orderId": "8B97F90B",
      "symbol": "BTCUSDT",
      "side": "BUY",
      "price": "89750.07673966182",
      "qty": "0.05",
      "commission": "1.7950015347932364",
      "realizedPnl": "0.0",
      "time": 1776775370507
    },
    {
      "tradeId": "0380C251",
      "orderId": "675F6303",
      "symbol": "BTCUSDT",
      "side": "SELL",
      "price": "87417.77513685782",
      "qty": "0.05",
      "commission": "1.7483555027371565",
      "realizedPnl": "-116.6150801402",
      "time": 1776775370667
    },
    {
      "tradeId": "45B43AFC",
      "orderId": "094FFBB1",
      "symbol": "BTCUSDT",
      "side": "SELL",
      "price": "87417.77513685782",
      "qty": "0.05",
      "commission": "1.7483555027371565",
      "realizedPnl": "0.0",
      "time": 1776775370668
    },
    {
      "tradeId": "5CC78C2E",
      "orderId": "71A5C063",
      "symbol": "BTCUSDT",
      "side": "BUY",
      "price": "88840.67769088129",
      "qty": "0.05",
      "commission": "1.776813553817626",
      "realizedPnl": "-71.14512770117362",
      "time": 1776775370897
    },
    {
      "tradeId": "CCB61B6C",
      "orderId": "8EA6D2C6",
      "symbol": "BTCUSDT",
      "side": "BUY",
      "price": "88840.67769088129",
      "qty": "0.05",
      "commission": "1.776813553817626",
      "realizedPnl": "0.0",
      "time": 1776775370898
    },
    {
      "tradeId": "C5C89321",
      "orderId": "2840E45F",
      "symbol": "BTCUSDT",
      "side": "SELL",
      "price": "88957.5075654249",
      "qty": "0.05",
      "commission": "1.779150151308498",
      "realizedPnl": "5.841493727180205",
      "time": 1776775370903
    },
    {
      "tradeId": "96137B6D",
      "orderId": "C0808FF5",
      "symbol": "BTCUSDT",
      "side": "SELL",
      "price": "88957.5075654249",
      "qty": "0.05",
      "commission": "1.779150151308498",
      "realizedPnl": "0.0",
      "time": 1776775370904
    },
    {
      "tradeId": "A39D678A",
      "orderId": "47BB9192",
      "symbol": "BTCUSDT",
      "side": "BUY",
      "price": "88268.81544784961",
      "qty": "0.05",
      "commission": "1.7653763089569923",
      "realizedPnl": "34.43460587876398",
      "time": 1776775370937
    },
    {
      "tradeId": "FB296DFD",
      "orderId": "0BB0A127",
      "symbol": "BTCUSDT",
      "side": "BUY",
      "price": "88268.81544784961",
      "qty": "0.05",
      "commission": "1.7653763089569923",
      "realizedPnl": "0.0",
      "time": 1776775370938
    },
    {
      "tradeId": "A315CE9A",
      "orderId": "F3AE4FB5",
      "symbol": "BTCUSDT",
      "side": "SELL",
      "price": "88958.30747830751",
      "qty": "0.05",
      "commission": "1.7791661495661506",
      "realizedPnl": "34.47460152289496",
      "time": 1776775371147
    },
    {
      "tradeId": "1F6F21D5",
      "orderId": "CC3C6704",
      "symbol": "BTCUSDT",
      "side": "SELL",
      "price": "88958.30747830751",
      "qty": "0.05",
      "commission": "1.7791661495661506",
      "realizedPnl": "0.0",
      "time": 1776775371148
    },
    {
      "tradeId": "F9D6C209",
      "orderId": "FBA0BB83",
      "symbol": "BTCUSDT",
      "side": "BUY",
      "price": "88746.26741275846",
      "qty": "0.05",
      "commission": "1.7749253482551692",
      "realizedPnl": "10.602003277452605",
      "time": 1776775371155
    },
    {
      "tradeId": "C09C610C",
      "orderId": "E3BAA16D",
      "symbol": "BTCUSDT",
      "side": "BUY",
      "price": "88746.26741275846",
      "qty": "0.05",
      "commission": "1.7749253482551692",
      "realizedPnl": "0.0",
      "time": 1776775371156
    },
    {
      "tradeId": "A34900A0",
      "orderId": "FA050E10",
      "symbol": "BTCUSDT",
      "side": "SELL",
      "price": "87594.5559095873",
      "qty": "0.05",
      "commission": "1.7518911181917463",
      "realizedPnl": "-57.585575158557916",
      "time": 1776775371376
    },
    {
      "tradeId": "04E10602",
      "orderId": "17845AAA",
      "symbol": "BTCUSDT",
      "side": "SELL",
      "price": "87594.5559095873",
      "qty": "0.05",
      "commission": "1.7518911181917463",
      "realizedPnl": "0.0",
      "time": 1776775371376
    },
    {
      "tradeId": "4FAEC6F9",
      "orderId": "35705107",
      "symbol": "BTCUSDT",
      "side": "BUY",
      "price": "88290.51780939648",
      "qty": "0.05",
      "commission": "1.7658103561879297",
      "realizedPnl": "-34.79809499045878",
      "time": 1776775371517
    },
    {
      "tradeId": "9026CBA3",
      "orderId": "F58BF415",
      "symbol": "BTCUSDT",
      "side": "BUY",
      "price": "88290.51780939648",
      "qty": "0.05",
      "commission": "1.7658103561879297",
      "realizedPnl": "0.0",
      "time": 1776775371518
    },
    {
      "tradeId": "DBF31F27",
      "orderId": "9EE53680",
      "symbol": "BTCUSDT",
      "side": "SELL",
      "price": "88345.57419146584",
      "qty": "0.05",
      "commission": "1.766911483829317",
      "realizedPnl": "2.7528191034682097",
      "time": 1776775371543
    },
    {
      "tradeId": "D4151D4E",
      "orderId": "6F32D17A",
      "symbol": "BTCUSDT",
      "side": "SELL",
      "price": "88345.57419146584",
      "qty": "0.05",
      "commission": "1.766911483829317",
      "realizedPnl": "0.0",
      "time": 1776775371544
    },
    {
      "tradeId": "A7AE0920",
      "orderId": "42B62D15",
      "symbol": "BTCUSDT",
      "side": "BUY",
      "price": "88612.7528790106",
      "qty": "0.05",
      "commission": "1.772255057580212",
      "realizedPnl": "-13.358934377237894",
      "time": 1776775371596
    },
    {
      "tradeId": "73EE67A6",
      "orderId": "8EB9408B",
      "symbol": "BTCUSDT",
      "side": "BUY",
      "price": "88612.7528790106",
      "qty": "0.05",
      "commission": "1.772255057580212",
      "realizedPnl": "0.0",
      "time": 1776775371597
    },
    {
      "tradeId": "813172B6",
      "orderId": "FFE3298B",
      "symbol": "BTCUSDT",
      "side": "SELL",
      "price": "89420.55712464929",
      "qty": "0.05",
      "commission": "1.788411142492986",
      "realizedPnl": "40.39021228193451",
      "time": 1776775371730
    },
    {
      "tradeId": "1A9B458A",
      "orderId": "AF035556",
      "symbol": "BTCUSDT",
      "side": "SELL",
      "price": "89420.55712464929",
      "qty": "0.05",
      "commission": "1.788411142492986",
      "realizedPnl": "0.0",
      "time": 1776775371731
    },
    {
      "tradeId": "E51424EC",
      "orderId": "C077467A",
      "symbol": "BTCUSDT",
      "side": "BUY",
      "price": "89467.64596937194",
      "qty": "0.05",
      "commission": "1.7893529193874387",
      "realizedPnl": "-2.3544422361323085",
      "time": 1776775371756
    },
    {
      "tradeId": "08877282",
      "orderId": "B7BEEFFE",
      "symbol": "BTCUSDT",
      "side": "BUY",
      "price": "89467.64596937194",
      "qty": "0.05",
      "commission": "1.7893529193874387",
      "realizedPnl": "0.0",
      "time": 1776775371757
    },
    {
      "tradeId": "7420A039",
      "orderId": "2B5D9E79",
      "symbol": "BTCUSDT",
      "side": "SELL",
      "price": "90324.5585884222",
      "qty": "0.05",
      "commission": "1.8064911717684442",
      "realizedPnl": "42.84563095251288",
      "time": 1776775371812
    },
    {
      "tradeId": "03E8DB73",
      "orderId": "B1BB13B8",
      "symbol": "BTCUSDT",
      "side": "SELL",
      "price": "90324.5585884222",
      "qty": "0.05",
      "commission": "1.8064911717684442",
      "realizedPnl": "0.0",
      "time": 1776775371813
    },
    {
      "tradeId": "DF81ED8A",
      "orderId": "4E1BB658",
      "symbol": "BTCUSDT",
      "side": "BUY",
      "price": "89744.6761512033",
      "qty": "0.05",
      "commission": "1.794893523024066",
      "realizedPnl": "28.994121860944873",
      "time": 1776775371835
    },
    {
      "tradeId": "BADB0C1E",
      "orderId": "28826C4B",
      "symbol": "BTCUSDT",
      "side": "BUY",
      "price": "89744.6761512033",
      "qty": "0.05",
      "commission": "1.794893523024066",
      "realizedPnl": "0.0",
      "time": 1776775371836
    },
    {
      "tradeId": "A7DC0D63",
      "orderId": "97A86F80",
      "symbol": "BTCUSDT",
      "side": "SELL",
      "price": "90520.8371832391",
      "qty": "0.05",
      "commission": "1.8104167436647822",
      "realizedPnl": "38.80805160179007",
      "time": 1776775372141
    },
    {
      "tradeId": "03AF914B",
      "orderId": "3B0DAAD8",
      "symbol": "BTCUSDT",
      "side": "SELL",
      "price": "90520.8371832391",
      "qty": "0.05",
      "commission": "1.8104167436647822",
      "realizedPnl": "0.0",
      "time": 1776775372142
    },
    {
      "tradeId": "D32D6158",
      "orderId": "52E7C0A2",
      "symbol": "BTCUSDT",
      "side": "BUY",
      "price": "91310.94693728209",
      "qty": "0.05",
      "commission": "1.826218938745642",
      "realizedPnl": "-39.50548770214955",
      "time": 1776775372182
    },
    {
      "tradeId": "C646744A",
      "orderId": "0508EBB3",
      "symbol": "BTCUSDT",
      "side": "BUY",
      "price": "91310.94693728209",
      "qty": "0.05",
      "commission": "1.826218938745642",
      "realizedPnl": "0.0",
      "time": 1776775372182
    },
    {
      "tradeId": "B5B26DDA",
      "orderId": "962FAB10",
      "symbol": "BTCUSDT",
      "side": "SELL",
      "price": "92358.43659670513",
      "qty": "0.05",
      "commission": "1.8471687319341026",
      "realizedPnl": "52.374482971151885",
      "time": 1776775372494
    },
    {
      "tradeId": "0E884093",
      "orderId": "084FF9F9",
      "symbol": "BTCUSDT",
      "side": "SELL",
      "price": "92358.43659670513",
      "qty": "0.05",
      "commission": "1.8471687319341026",
      "realizedPnl": "0.0",
      "time": 1776775372495
    },
    {
      "tradeId": "8472E6DC",
      "orderId": "4FC21B4A",
      "symbol": "BTCUSDT",
      "side": "BUY",
      "price": "92566.48401806132",
      "qty": "0.05",
      "commission": "1.8513296803612267",
      "realizedPnl": "-10.402371067809874",
      "time": 1776775372543
    },
    {
      "tradeId": "DDB5AF49",
      "orderId": "B23813A8",
      "symbol": "BTCUSDT",
      "side": "BUY",
      "price": "92566.48401806132",
      "qty": "0.05",
      "commission": "1.8513296803612267",
      "realizedPnl": "0.0",
      "time": 1776775372544
    },
    {
      "tradeId": "4A1C5EF1",
      "orderId": "5FD64184",
      "symbol": "BTCUSDT",
      "side": "SELL",
      "price": "93890.069150439",
      "qty": "0.05",
      "commission": "1.87780138300878",
      "realizedPnl": "66.17925661888367",
      "time": 1776775372654
    },
    {
      "tradeId": "799B4670",
      "orderId": "4A573360",
      "symbol": "BTCUSDT",
      "side": "SELL",
      "price": "93890.069150439",
      "qty": "0.05",
      "commission": "1.87780138300878",
      "realizedPnl": "0.0",
      "time": 1776775372655
    },
    {
      "tradeId": "CD498130",
      "orderId": "366AE297",
      "symbol": "BTCUSDT",
      "side": "BUY",
      "price": "93656.40314428457",
      "qty": "0.05",
      "commission": "1.8731280628856917",
      "realizedPnl": "11.68330030772122",
      "time": 1776775372665
    },
    {
      "tradeId": "D230E206",
      "orderId": "A15B6F74",
      "symbol": "BTCUSDT",
      "side": "BUY",
      "price": "93656.40314428457",
      "qty": "0.05",
      "commission": "1.8731280628856917",
      "realizedPnl": "0.0",
      "time": 1776775372666
    },
    {
      "tradeId": "895F07DD",
      "orderId": "8F7F7561",
      "symbol": "BTCUSDT",
      "side": "SELL",
      "price": "94263.12833007355",
      "qty": "0.05",
      "commission": "1.8852625666014713",
      "realizedPnl": "30.336259289448936",
      "time": 1776775372686
    },
    {
      "tradeId": "9B744320",
      "orderId": "AAEAC952",
      "symbol": "BTCUSDT",
      "side": "SELL",
      "price": "94263.12833007355",
      "qty": "0.05",
      "commission": "1.8852625666014713",
      "realizedPnl": "0.0",
      "time": 1776775372687
    },
    {
      "tradeId": "E30557F9",
      "orderId": "EB8B8927",
      "symbol": "BTCUSDT",
      "side": "BUY",
      "price": "94258.4689999301",
      "qty": "0.05",
      "commission": "1.885169379998602",
      "realizedPnl": "0.23296650717238665",
      "time": 1776775372714
    },
    {
      "tradeId": "6ED27534",
      "orderId": "5450D41D",
      "symbol": "BTCUSDT",
      "side": "BUY",
      "price": "94258.4689999301",
      "qty": "0.05",
      "commission": "1.885169379998602",
      "realizedPnl": "0.0",
      "time": 1776775372715
    },
    {
      "tradeId": "AA11553F",
      "orderId": "85CCA6BD",
      "symbol": "BTCUSDT",
      "side": "SELL",
      "price": "92660.70356984819",
      "qty": "0.05",
      "commission": "1.853214071396964",
      "realizedPnl": "-79.88827150409561",
      "time": 1776775373068
    },
    {
      "tradeId": "BD830503",
      "orderId": "989823DB",
      "symbol": "BTCUSDT",
      "side": "SELL",
      "price": "92660.70356984819",
      "qty": "0.05",
      "commission": "1.853214071396964",
      "realizedPnl": "0.0",
      "time": 1776775373069
    },
    {
      "tradeId": "52D28754",
      "orderId": "08C1A4A9",
      "symbol": "BTCUSDT",
      "side": "BUY",
      "price": "91312.6471228035",
      "qty": "0.05",
      "commission": "1.82625294245607",
      "realizedPnl": "67.40282235223495",
      "time": 1776775373243
    },
    {
      "tradeId": "43E4F209",
      "orderId": "AC329403",
      "symbol": "BTCUSDT",
      "side": "BUY",
      "price": "91312.6471228035",
      "qty": "0.05",
      "commission": "1.82625294245607",
      "realizedPnl": "0.0",
      "time": 1776775373244
    },
    {
      "tradeId": "1BDB4F6C",
      "orderId": "A21BD103",
      "symbol": "BTCUSDT",
      "side": "SELL",
      "price": "91006.08424802784",
      "qty": "0.05",
      "commission": "1.8201216849605568",
      "realizedPnl": "-15.32814373878282",
      "time": 1776775373305
    },
    {
      "tradeId": "FAE030BE",
      "orderId": "5B3D1008",
      "symbol": "BTCUSDT",
      "side": "SELL",
      "price": "91006.08424802784",
      "qty": "0.05",
      "commission": "1.8201216849605568",
      "realizedPnl": "0.0",
      "time": 1776775373306
    },
    {
      "tradeId": "8144BAA0",
      "orderId": "7DFD5DD7",
      "symbol": "BTCUSDT",
      "side": "BUY",
      "price": "90739.48459664501",
      "qty": "0.05",
      "commission": "1.8147896919329003",
      "realizedPnl": "13.32998256914143",
      "time": 1776775373560
    },
    {
      "tradeId": "2288E6D1",
      "orderId": "AC713DC3",
      "symbol": "BTCUSDT",
      "side": "BUY",
      "price": "90739.48459664501",
      "qty": "0.05",
      "commission": "1.8147896919329003",
      "realizedPnl": "0.0",
      "time": 1776775373560
    },
    {
      "tradeId": "4DD9FF49",
      "orderId": "3E0A447C",
      "symbol": "BTCUSDT",
      "side": "SELL",
      "price": "90434.14663776096",
      "qty": "0.05",
      "commission": "1.8086829327552194",
      "realizedPnl": "-15.266897944202356",
      "time": 1776775373781
    },
    {
      "tradeId": "9A8E45B2",
      "orderId": "2C7361E4",
      "symbol": "BTCUSDT",
      "side": "SELL",
      "price": "90434.14663776096",
      "qty": "0.05",
      "commission": "1.8086829327552194",
      "realizedPnl": "0.0",
      "time": 1776775373782
    },
    {
      "tradeId": "3F041CB1",
      "orderId": "EFD2C2E9",
      "symbol": "BTCUSDT",
      "side": "BUY",
      "price": "90659.07582749901",
      "qty": "0.05",
      "commission": "1.8131815165499805",
      "realizedPnl": "-11.246459486902314",
      "time": 1776775373945
    },
    {
      "tradeId": "4E30B99F",
      "orderId": "09D7A6E5",
      "symbol": "BTCUSDT",
      "side": "BUY",
      "price": "90659.07582749901",
      "qty": "0.05",
      "commission": "1.8131815165499805",
      "realizedPnl": "0.0",
      "time": 1776775373946
    },
    {
      "tradeId": "CD8DCBD3",
      "orderId": "546A89BD",
      "symbol": "BTCUSDT",
      "side": "SELL",
      "price": "90879.79802675729",
      "qty": "0.05",
      "commission": "1.817595960535146",
      "realizedPnl": "11.036109962913907",
      "time": 1776775374351
    },
    {
      "tradeId": "57DDEC23",
      "orderId": "984F8A08",
      "symbol": "BTCUSDT",
      "side": "SELL",
      "price": "90879.79802675729",
      "qty": "0.05",
      "commission": "1.817595960535146",
      "realizedPnl": "0.0",
      "time": 1776775374352
    },
    {
      "tradeId": "1D1950B7",
      "orderId": "70E9DCB3",
      "symbol": "BTCUSDT",
      "side": "BUY",
      "price": "91084.32221095976",
      "qty": "0.05",
      "commission": "1.8216864442191953",
      "realizedPnl": "-10.22620921012349",
      "time": 1776775374375
    },
    {
      "tradeId": "4DCC72FB",
      "orderId": "4D41EC93",
      "symbol": "BTCUSDT",
      "side": "BUY",
      "price": "91084.32221095976",
      "qty": "0.05",
      "commission": "1.8216864442191953",
      "realizedPnl": "0.0",
      "time": 1776775374376
    },
    {
      "tradeId": "DA640A30",
      "orderId": "1FFF2DEE",
      "symbol": "BTCUSDT",
      "side": "SELL",
      "price": "91219.56095256566",
      "qty": "0.05",
      "commission": "1.8243912190513134",
      "realizedPnl": "6.76193708029532",
      "time": 1776775374501
    },
    {
      "tradeId": "84593215",
      "orderId": "A6E09CC7",
      "symbol": "BTCUSDT",
      "side": "SELL",
      "price": "91219.56095256566",
      "qty": "0.05",
      "commission": "1.8243912190513134",
      "realizedPnl": "0.0",
      "time": 1776775374502
    },
    {
      "tradeId": "4B41514F",
      "orderId": "13A91526",
      "symbol": "BTCUSDT",
      "side": "BUY",
      "price": "92076.2304729418",
      "qty": "0.05",
      "commission": "1.8415246094588362",
      "realizedPnl": "-42.83347601880669",
      "time": 1776775374548
    },
    {
      "tradeId": "BA0F7832",
      "orderId": "80DD58E5",
      "symbol": "BTCUSDT",
      "side": "BUY",
      "price": "92076.2304729418",
      "qty": "0.05",
      "commission": "1.8415246094588362",
      "realizedPnl": "0.0",
      "time": 1776775374549
    },
    {
      "tradeId": "D9A5ADA1",
      "orderId": "CE7AB62C",
      "symbol": "BTCUSDT",
      "side": "SELL",
      "price": "90996.08533903844",
      "qty": "0.05",
      "commission": "1.8199217067807691",
      "realizedPnl": "-54.0072566951676",
      "time": 1776775374716
    },
    {
      "tradeId": "028EBDF3",
      "orderId": "F3EDDD32",
      "symbol": "BTCUSDT",
      "side": "SELL",
      "price": "90996.08533903844",
      "qty": "0.05",
      "commission": "1.8199217067807691",
      "realizedPnl": "0.0",
      "time": 1776775374717
    },
    {
      "tradeId": "CA6380EF",
      "orderId": "E51DFAC6",
      "symbol": "BTCUSDT",
      "side": "BUY",
      "price": "93200.35328439643",
      "qty": "0.05",
      "commission": "1.8640070656879288",
      "realizedPnl": "-110.21339726789957",
      "time": 1776775374911
    },
    {
      "tradeId": "7B1273F3",
      "orderId": "20470CF5",
      "symbol": "BTCUSDT",
      "side": "BUY",
      "price": "93200.35328439643",
      "qty": "0.05",
      "commission": "1.8640070656879288",
      "realizedPnl": "0.0",
      "time": 1776775374912
    },
    {
      "tradeId": "AE460238",
      "orderId": "D397E514",
      "symbol": "BTCUSDT",
      "side": "SELL",
      "price": "94169.63856108898",
      "qty": "0.05",
      "commission": "1.88339277122178",
      "realizedPnl": "48.464263834627495",
      "time": 1776775374934
    },
    {
      "tradeId": "537BB708",
      "orderId": "4CF0C52D",
      "symbol": "BTCUSDT",
      "side": "SELL",
      "price": "94169.63856108898",
      "qty": "0.05",
      "commission": "1.88339277122178",
      "realizedPnl": "0.0",
      "time": 1776775374936
    },
    {
      "tradeId": "81E1776B",
      "orderId": "0BE345D7",
      "symbol": "BTCUSDT",
      "side": "BUY",
      "price": "94049.84617608",
      "qty": "0.05",
      "commission": "1.8809969235216002",
      "realizedPnl": "5.989619250449323",
      "time": 1776775374965
    },
    {
      "tradeId": "10355BA6",
      "orderId": "E398DDAD",
      "symbol": "BTCUSDT",
      "side": "BUY",
      "price": "94049.84617608",
      "qty": "0.05",
      "commission": "1.8809969235216002",
      "realizedPnl": "0.0",
      "time": 1776775374966
    },
    {
      "tradeId": "99403AE9",
      "orderId": "0D1749ED",
      "symbol": "BTCUSDT",
      "side": "SELL",
      "price": "94527.5993830547",
      "qty": "0.05",
      "commission": "1.890551987661094",
      "realizedPnl": "23.88766034873479",
      "time": 1776775375598
    },
    {
      "tradeId": "EE052122",
      "orderId": "960D0680",
      "symbol": "BTCUSDT",
      "side": "SELL",
      "price": "94527.5993830547",
      "qty": "0.05",
      "commission": "1.890551987661094",
      "realizedPnl": "0.0",
      "time": 1776775375599
    },
    {
      "tradeId": "D54FA53E",
      "orderId": "62DE6691",
      "symbol": "BTCUSDT",
      "side": "BUY",
      "price": "94836.53226420337",
      "qty": "0.05",
      "commission": "1.8967306452840678",
      "realizedPnl": "-15.446644057433879",
      "time": 1776775375608
    },
    {
      "tradeId": "123E8B45",
      "orderId": "66D36D3C",
      "symbol": "BTCUSDT",
      "side": "BUY",
      "price": "94836.53226420337",
      "qty": "0.05",
      "commission": "1.8967306452840678",
      "realizedPnl": "0.0",
      "time": 1776775375608
    },
    {
      "tradeId": "FDF9C47C",
      "orderId": "78EA5BAD",
      "symbol": "BTCUSDT",
      "side": "SELL",
      "price": "95386.20535825127",
      "qty": "0.05",
      "commission": "1.9077241071650257",
      "realizedPnl": "27.483654702395143",
      "time": 1776775376192
    },
    {
      "tradeId": "9C1BE63B",
      "orderId": "0E0DF585",
      "symbol": "BTCUSDT",
      "side": "SELL",
      "price": "95386.20535825127",
      "qty": "0.05",
      "commission": "1.9077241071650257",
      "realizedPnl": "0.0",
      "time": 1776775376193
    },
    {
      "tradeId": "5D40979C",
      "orderId": "0D065890",
      "symbol": "BTCUSDT",
      "side": "BUY",
      "price": "95269.27964671182",
      "qty": "0.05",
      "commission": "1.9053855929342365",
      "realizedPnl": "5.846285576972878",
      "time": 1776775376216
    },
    {
      "tradeId": "9085EA51",
      "orderId": "8AD169E6",
      "symbol": "BTCUSDT",
      "side": "BUY",
      "price": "95269.27964671182",
      "qty": "0.05",
      "commission": "1.9053855929342365",
      "realizedPnl": "0.0",
      "time": 1776775376217
    },
    {
      "tradeId": "DF31731B",
      "orderId": "EE4F2994",
      "symbol": "BTCUSDT",
      "side": "SELL",
      "price": "95432.90024264198",
      "qty": "0.05",
      "commission": "1.9086580048528394",
      "realizedPnl": "8.181029796507937",
      "time": 1776775376240
    },
    {
      "tradeId": "641BA758",
      "orderId": "718C92E8",
      "symbol": "BTCUSDT",
      "side": "SELL",
      "price": "95432.90024264198",
      "qty": "0.05",
      "commission": "1.9086580048528394",
      "realizedPnl": "0.0",
      "time": 1776775376240
    },
    {
      "tradeId": "FE3FC116",
      "orderId": "1798DE9D",
      "symbol": "BTCUSDT",
      "side": "BUY",
      "price": "93623.7995790498",
      "qty": "0.05",
      "commission": "1.8724759915809959",
      "realizedPnl": "90.45503317960902",
      "time": 1776775376254
    },
    {
      "tradeId": "24A719C5",
      "orderId": "DFF41533",
      "symbol": "BTCUSDT",
      "side": "BUY",
      "price": "93623.7995790498",
      "qty": "0.05",
      "commission": "1.8724759915809959",
      "realizedPnl": "0.0",
      "time": 1776775376255
    },
    {
      "tradeId": "DEEAAE25",
      "orderId": "D7096586",
      "symbol": "BTCUSDT",
      "side": "SELL",
      "price": "92646.90507772383",
      "qty": "0.05",
      "commission": "1.8529381015544768",
      "realizedPnl": "-48.844725066298274",
      "time": 1776775376316
    },
    {
      "tradeId": "19D69ED8",
      "orderId": "3D88C29B",
      "symbol": "BTCUSDT",
      "side": "SELL",
      "price": "92646.90507772383",
      "qty": "0.05",
      "commission": "1.8529381015544768",
      "realizedPnl": "0.0",
      "time": 1776775376318
    },
    {
      "tradeId": "DA6A0E46",
      "orderId": "BDE3C26F",
      "symbol": "BTCUSDT",
      "side": "BUY",
      "price": "87571.43958781907",
      "qty": "0.05",
      "commission": "1.7514287917563816",
      "realizedPnl": "253.773274495238",
      "time": 1776775376968
    },
    {
      "tradeId": "1F2C539F",
      "orderId": "71283A18",
      "symbol": "BTCUSDT",
      "side": "BUY",
      "price": "87571.43958781907",
      "qty": "0.05",
      "commission": "1.7514287917563816",
      "realizedPnl": "0.0",
      "time": 1776775376969
    },
    {
      "tradeId": "C5D81812",
      "orderId": "EC898250",
      "symbol": "BTCUSDT",
      "side": "SELL",
      "price": "87887.82400586955",
      "qty": "0.05",
      "commission": "1.757756480117391",
      "realizedPnl": "15.819220902524103",
      "time": 1776775376976
    },
    {
      "tradeId": "1452F5E1",
      "orderId": "8289984B",
      "symbol": "BTCUSDT",
      "side": "SELL",
      "price": "87887.82400586955",
      "qty": "0.05",
      "commission": "1.757756480117391",
      "realizedPnl": "0.0",
      "time": 1776775376977
    }
  ]
}